aio_pytumblr/__init__.py
aio_pytumblr/helpers.py
aio_pytumblr/request.py
PyTumblr_aio-0.0.2.dist-info/LICENSE
PyTumblr_aio-0.0.2.dist-info/METADATA
PyTumblr_aio-0.0.2.dist-info/WHEEL
PyTumblr_aio-0.0.2.dist-info/top_level.txt
PyTumblr_aio-0.0.2.dist-info/RECORD
