Metadata-Version: 2.1
Name: PyTumblr-aio
Version: 0.0.2
Summary: An Async Python Tumblr API v2 Client
Home-page: https://github.com/dj-ratty/pytumblr-aio
Download-URL: https://github.com/tumblr/pytumblr/archive/0.1.1.tar.gz
Author: dj-ratty
Author-email: Tumblr <accounts@tumblr.com>, dj-ratty <115014503+dj-ratty@users.noreply.github.com>
License: 
Project-URL: Homepage, https://github.com/dj-ratty/pytumblr-aio
Project-URL: Bug Tracker, https://github.com/dj-ratty/pytumblr-aio/issues
Project-URL: Download, https://github.com/dj-ratty/pytumblr-aio/releases
Keywords: pytumblr pytumblr-aio aio_pytumblr
Classifier: Development Status :: 3 - Alpha
Classifier: Intended Audience :: Developers
Classifier: Natural Language :: English
Classifier: Programming Language :: Python :: 3.7
Classifier: Programming Language :: Python :: 3.8
Classifier: Programming Language :: Python :: 3.9
Classifier: Programming Language :: Python :: 3.10
Requires-Python: >=3.7
License-File: LICENSE
Requires-Dist: httpx
Requires-Dist: Authlib
Provides-Extra: aiounittest
Requires-Dist: aiounittest ; extra == 'aiounittest'
Provides-Extra: mock
Requires-Dist: mock ; extra == 'mock'
Provides-Extra: nose
Requires-Dist: nose ; extra == 'nose'
Provides-Extra: nosecov
Requires-Dist: nose-cov ; extra == 'nosecov'
